libsbdart.cpython-311-x86_64-linux-gnu.so
libsmarts_295.cpython-311-x86_64-linux-gnu.so
AtmosRT-0.5.9.data/scripts/smarts-exe.py
AtmosRT-0.5.9.data/scripts/sbdart-exe.py
AtmosRT-0.5.9.dist-info/top_level.txt
AtmosRT-0.5.9.dist-info/WHEEL
AtmosRT-0.5.9.dist-info/RECORD
AtmosRT-0.5.9.dist-info/METADATA
atmosrt/smarts-exe.py
atmosrt/sbdart-exe.py
atmosrt/settings.py
atmosrt/sbdart.py
atmosrt/smarts.py
atmosrt/_rtm.py
atmosrt/__init__.py
AtmosRT.libs/libquadmath-96973f99.so.0.0.0
AtmosRT.libs/libgfortran-040039e1.so.5.0.0
