Metadata-Version: 2.1
Name: AtmosRT
Version: 0.5.9
Summary: Atmospheric Radiative Transfer Model interface
Home-page: https://github.com/ghislainp/atmosrt
Author: Ghislain Picard
Author-email: ghipicard@gmail.com
License: GPLv3
Classifier: License :: OSI Approved :: MIT License
Classifier: Programming Language :: Python :: 3
Classifier: Programming Language :: Python :: 3.7
Requires-Dist: numpy
Requires-Dist: pandas
Requires-Dist: msgpack-python
Requires-Dist: snowoptics
